QApedia/__init__.py
QApedia/generator.py
QApedia/io.py
QApedia/utils.py
tests/__init__.py
tests/conftest.py
tests/test_generator.py
tests/test_io.py
tests/test_utils.py
QApedia-0.0.dist-info/LICENSE
QApedia-0.0.dist-info/METADATA
QApedia-0.0.dist-info/WHEEL
QApedia-0.0.dist-info/top_level.txt
QApedia-0.0.dist-info/RECORD
