Metadata-Version: 2.1
Name: QApedia
Version: 0.0
Summary: UNKNOWN
Home-page: https://github.com/JessicaSousa/QApedia
Author: Jessica Sousa
Author-email: jessicasousa.pc@gmail.com
License: MIT License
Requires-Dist: SPARQLWrapper
Requires-Dist: pandas
